README.rst
setup.py
django_sticky_files.egg-info/PKG-INFO
django_sticky_files.egg-info/SOURCES.txt
django_sticky_files.egg-info/dependency_links.txt
django_sticky_files.egg-info/not-zip-safe
django_sticky_files.egg-info/top_level.txt
sticky_files/__init__.py
sticky_files/admin.py
sticky_files/apps.py
sticky_files/fields.py
sticky_files/forms.py
sticky_files/models.py
sticky_files/urls.py
sticky_files/views.py
sticky_files/widgets.py
sticky_files/management/__init__.py
sticky_files/management/commands/__init__.py
sticky_files/migrations/0001_initial.py
sticky_files/migrations/__init__.py
sticky_files/static/sticky_files/css/sticky_uploader.css
sticky_files/static/sticky_files/css/sticky_uploader.css.map
sticky_files/static/sticky_files/img/.gitkeep
sticky_files/static/sticky_files/img/cameraicon.png
sticky_files/static/sticky_files/img/document.png
sticky_files/static/sticky_files/img/trash.png
sticky_files/static/sticky_files/js/main.js
sticky_files/static/sticky_files/js/main.js.map
sticky_files/static/sticky_files/js/sticky_uploader.js
sticky_files/static/sticky_files/js/sticky_uploader.js.map
sticky_files/templates/sticky_files/widgets/many_file_widget.html
sticky_files/templates/sticky_files/widgets/many_image_widget.html
sticky_files/templates/sticky_files/widgets/one_file_widget.html
sticky_files/templates/sticky_files/widgets/one_image_widget.html
sticky_files/templatetags/__init__.py
sticky_files/templatetags/sticky_files_tags.py
sticky_files/tests/__init__.py
sticky_files/tests/test_models.py