Metadata-Version: 1.1
Name: django-sticky-files
Version: 0.3.2
Summary: Application to make Django file fields save their values between page reloads
Home-page: https://github.com/asyncee/django-sticky-files
Author: asyncee
Author-email: UNKNOWN
License: MIT
Download-URL: https://pypi.python.org/pypi/django-sticky-files/
Keywords: django sticky_files
Platform: UNKNOWN
Classifier: Development Status :: 3 - Alpha
Classifier: Environment :: Web Environment
Classifier: Framework :: Django
Classifier: Intended Audience :: Developers
Classifier: License :: OSI Approved :: MIT License
Classifier: Programming Language :: Python
Classifier: Programming Language :: Python :: 3
Classifier: Topic :: Software Development :: Widget Sets
